lmsp/__init__.py
lmsp/cli.py
lmsp-0.5.7.dist-info/licenses/LICENSE
lmsp-0.5.7.dist-info/METADATA
lmsp-0.5.7.dist-info/WHEEL
lmsp-0.5.7.dist-info/entry_points.txt
lmsp-0.5.7.dist-info/top_level.txt
lmsp-0.5.7.dist-info/RECORD
